ochrepy/__init__.py
ochrepy/auth.py
ochrepy/cache_handler.py
ochrepy/client.py
ochrepy/exceptions.py
ochrepy/util.py
ochrepy/cms/__init__.py
ochrepy/cms/modules.py
ochrepy/cms/spaces.py
ochrepy/cms/views.py
ochrepy/music/__init__.py
ochrepy/music/artists.py
ochrepy/music/labels.py
ochrepy/music/media_items.py
ochrepy/music/releases.py
ochrepy/music/tracks.py
ochrepy/retail/__init__.py
ochrepy/retail/carts.py
ochrepy/retail/order_items.py
ochrepy/retail/orders.py
ochrepy/retail/products.py
ochrepy/retail/stores.py
ochrepy-1.0.1.dist-info/LICENSE.md
ochrepy-1.0.1.dist-info/METADATA
ochrepy-1.0.1.dist-info/WHEEL
ochrepy-1.0.1.dist-info/top_level.txt
ochrepy-1.0.1.dist-info/RECORD
