Metadata-Version: 2.1
Name: ochrepy
Version: 1.0.1
Summary: A light weight Python library for the Ochre Web API
Author: Jopgood
Author-email: jehopgood@gmail.com
License: MIT
Project-URL: Source, https://github.com/Jopgood/ochrepy
Requires-Python: >3.8
License-File: LICENSE.md
Requires-Dist: requests >=2.25.0
Requires-Dist: urllib3 >=1.26.0
Provides-Extra: memcache
Requires-Dist: pymemcache >=3.5.2 ; extra == 'memcache'
